LICENSE
MANIFEST.in
README.md
setup.py
five/__init__.py
five/five.py
five.egg-info/PKG-INFO
five.egg-info/SOURCES.txt
five.egg-info/dependency_links.txt
five.egg-info/top_level.txt
five/test/test_five.py