Metadata-Version: 1.1
Name: five
Version: 0.3.0
Summary: Gives you five. A library to overcomplicate `5`
Home-page: http://github.com/lord63/five.py
Author: lord63
Author-email: lord63.j@gmail.com
License: MIT
Keywords: five fun
Platform: UNKNOWN
Classifier: Development Status :: 4 - Beta
Classifier: Operating System :: POSIX
Classifier: Operating System :: POSIX :: Linux
Classifier: License :: OSI Approved :: MIT License
Classifier: Programming Language :: Python :: 2
Classifier: Programming Language :: Python :: 2.7
Classifier: Programming Language :: Python :: 3
Classifier: Programming Language :: Python :: 3.3
Classifier: Programming Language :: Python :: 3.4
